dynamodbusermanager/__init__.py
dynamodbusermanager/cli.py
dynamodbusermanager/constants.py
dynamodbusermanager/daemon.py
dynamodbusermanager/entity.py
dynamodbusermanager/export.py
dynamodbusermanager/group.py
dynamodbusermanager/shadow.py
dynamodbusermanager/user.py
dynamodbusermanager/utils.py
dynamodb_user_manager-1.0.2.dist-info/LICENSE
dynamodb_user_manager-1.0.2.dist-info/METADATA
dynamodb_user_manager-1.0.2.dist-info/WHEEL
dynamodb_user_manager-1.0.2.dist-info/entry_points.txt
dynamodb_user_manager-1.0.2.dist-info/top_level.txt
dynamodb_user_manager-1.0.2.dist-info/RECORD
