Metadata-Version: 2.1
Name: dynamodb-user-manager
Version: 1.0.2
Summary: Manage the local user database from DynamoDB
Home-page: https://github.com/dacut/dynamodb-user-manager
Author: David Cuthbert
Author-email: dacut@kanga.org
License: Apache-2.0
Platform: UNKNOWN
Requires-Python: >=3.6
Requires-Dist: boto3 (>=1.16)
Requires-Dist: daemonize (>=2.5.0)
Requires-Dist: requests (>=2.25)
